{
    "PaladinMod:AuraOfCouragePower": {
        "NAME": "Aura of Courage",
        "DESCRIPTIONS": [
            "You can no longer be weakened."
        ]
    },

    "PaladinMod:AuraOfHatePower": {
        "NAME": "Aura of Hate",
        "DESCRIPTIONS": [
            "At the start of your turn, if your #yDivinity is negative, gain #b",
            " #yStrength."
        ]
    },

    "PaladinMod:AuraOfPurityPower": {
        "NAME": "Aura of Purity",
        "DESCRIPTIONS": [
            "Whenever you draw a #yStatus card, #yExhaust it."
        ]
    },

    "PaladinMod:DivinityPower": {
        "NAME": "Divinity",
        "DESCRIPTIONS": [
            "Paladin #yDivinity level."
        ]
    },

    "PaladinMod:GuidingHandPower": {
        "NAME": "Guiding Hand",
        "DESCRIPTIONS": [
            "Next turn, #b",
            " costs one less."
        ]
    },

    "PaladinMod:HammerTossPower": {
        "NAME": "Hammer Tossed",
        "DESCRIPTIONS": [
            "Next turn, you cannot play attacks."
        ]
    },

    "PaladinMod:NeowArsenalPower": {
        "NAME": "Neow's Arsenal",
        "DESCRIPTIONS": [
            "At the start of your turn, add #b",
            " random #ySmite card into your hand.",
            " random #ySmite cards into your hand."
        ]
    },

    "PaladinMod:OathbreakerPower": {
        "NAME": "Oathbreaker",
        "DESCRIPTIONS": [
            "Your Divinity can no longer go positve."
        ]
    },

    "PaladinMod:RedemptionPower": {
        "NAME": "Redemption",
        "DESCRIPTIONS": [
            "Your Divinity can no longer go negative."
        ]
    },

    "PaladinMod:WayOfProtectionPower": {
        "NAME": "Way of Protection",
        "DESCRIPTIONS": [
            "Whenever you gain #yDivinity, gain #b",
            " #yBlock."
        ]
    },

    "PaladinMod:WayOfVengeancePower": {
        "NAME": "Way of Vengeance",
        "DESCRIPTIONS": [
            "Whenever you gain #yDivinity, deal #b",
            " damage to a random enemy."
        ]
    },

    "DO_NOT_REMOVE_DummyLineForJSONEndOfFile": {}
}